photon_flux_estimation/__init__.py
photon_flux_estimation/core.py
photon_flux_estimation/visualization.py
photon_flux_estimation-0.1.1.dist-info/licenses/LICENSE
photon_flux_estimation-0.1.1.dist-info/METADATA
photon_flux_estimation-0.1.1.dist-info/WHEEL
photon_flux_estimation-0.1.1.dist-info/top_level.txt
photon_flux_estimation-0.1.1.dist-info/RECORD
