Metadata-Version: 2.4
Name: photon-flux-estimation
Version: 0.1.1
Summary: Library to compute estimated photon flux from multiphoton imaging data
Home-page: https://github.com/catalystneuro/photon-flux-estimation
Author: Alessandra Trapani
Author-email: alessandra.trapani@catalystneuro.com
Requires-Python: >=3.8
License-File: LICENSE
Requires-Dist: numpy
Requires-Dist: scikit-learn
Requires-Dist: matplotlib
Requires-Dist: pynwb
Requires-Dist: dandi
Requires-Dist: h5py
Requires-Dist: colorcet
Requires-Dist: fsspec
Dynamic: author
Dynamic: author-email
Dynamic: description
Dynamic: description-content-type
Dynamic: home-page
Dynamic: license-file
Dynamic: requires-dist
Dynamic: requires-python
Dynamic: summary
